pygge/__init__.py
pygge/base_gge_socket.py
pygge/gge_socket.py
pygge/account/__init__.py
pygge/account/account.py
pygge/account/auth.py
pygge/account/emblem.py
pygge/account/friends.py
pygge/account/settings.py
pygge/alliance/__init__.py
pygge/alliance/chat.py
pygge/alliance/help.py
pygge/army/__init__.py
pygge/army/hospital.py
pygge/army/soldiers.py
pygge/army/tools.py
pygge/army/units.py
pygge/building/__init__.py
pygge/building/buildings.py
pygge/building/buildings_inventory.py
pygge/building/extension.py
pygge/building/repair.py
pygge/building/wall.py
pygge/castle/__init__.py
pygge/castle/castle.py
pygge/castle/defense.py
pygge/events/__init__.py
pygge/events/beyond_the_horizon.py
pygge/events/events.py
pygge/events/fortune_teller.py
pygge/events/imperial_patronage.py
pygge/events/lucky_wheel.py
pygge/events/mercenary_camp.py
pygge/events/outer_realms.py
pygge/events/storm_islands.py
pygge/events/technicus.py
pygge/events/wishing_well.py
pygge/generals/__init__.py
pygge/generals/tavern.py
pygge/gifts/__init__.py
pygge/gifts/castle_gifts.py
pygge/gifts/daily_gifts.py
pygge/gifts/gifts.py
pygge/lords/__init__.py
pygge/lords/lords.py
pygge/map/__init__.py
pygge/map/attack.py
pygge/map/bookmarks.py
pygge/map/map.py
pygge/map/movements.py
pygge/map/ruins.py
pygge/map/spy.py
pygge/misc/__init__.py
pygge/misc/build_items.py
pygge/misc/global_effects.py
pygge/misc/quests.py
pygge/misc/tax.py
pygge/shop/__init__.py
pygge/shop/bestseller.py
pygge/shop/kings_market.py
pygge/shop/shop.py
pygge/shop/shopping_cart.py
pygge/shop/special_offers.py
pygge/shop/specialist.py
pygge/tutorial/__init__.py
pygge/tutorial/tutorial.py
pygge/utils/__init__.py
pygge/utils/recaptcha.py
pygge/utils/system.py
pygge-2.2.6.dist-info/METADATA
pygge-2.2.6.dist-info/WHEEL
pygge-2.2.6.dist-info/top_level.txt
pygge-2.2.6.dist-info/RECORD
