Metadata-Version: 2.4
Name: pygge
Version: 2.2.6
Summary: A Python library for interacting with GoodGame Empire API.
Home-page: https://github.com/danadum/pygge
Author: danadum
Author-email: danadum.empire@gmail.com
Classifier: Development Status :: 3 - Alpha
Classifier: Intended Audience :: Developers
Classifier: Topic :: Software Development :: Libraries
Classifier: Programming Language :: Python :: 3
Classifier: License :: OSI Approved :: MIT License
Classifier: Operating System :: OS Independent
Requires-Python: >=3.7
Requires-Dist: requests>=2.31.0
Requires-Dist: websocket-client>=1.8.0
Requires-Dist: selenium>=4.32.0
Dynamic: author
Dynamic: author-email
Dynamic: classifier
Dynamic: home-page
Dynamic: requires-dist
Dynamic: requires-python
Dynamic: summary
